gonio_analysis-0.8.10.dist-info/licenses/LICENSE
gonioanalysis/__init__.py
gonioanalysis/antenna_level.py
gonioanalysis/binary_search.py
gonioanalysis/coordinates.py
gonioanalysis/directories.py
gonioanalysis/droso.py
gonioanalysis/image_tools.py
gonioanalysis/rotary_encoders.py
gonioanalysis/settings.py
gonioanalysis/version.py
gonioanalysis/drosom/README.txt
gonioanalysis/drosom/__init__.py
gonioanalysis/drosom/analyser_commands.py
gonioanalysis/drosom/analysers.py
gonioanalysis/drosom/analysing.py
gonioanalysis/drosom/export.py
gonioanalysis/drosom/fitting.py
gonioanalysis/drosom/kinematics.py
gonioanalysis/drosom/loading.py
gonioanalysis/drosom/optic_flow.py
gonioanalysis/drosom/orientation_analysis.py
gonioanalysis/drosom/sinesweep.py
gonioanalysis/drosom/startpos_analysis.py
gonioanalysis/drosom/terminal.py
gonioanalysis/drosom/transmittance_analysis.py
gonioanalysis/drosom/virtual_analyser.py
gonioanalysis/drosom/linked_data/__init__.py
gonioanalysis/drosom/linked_data/electrophysiology.py
gonioanalysis/drosom/plotting/__init__.py
gonioanalysis/drosom/plotting/ax3d.py
gonioanalysis/drosom/plotting/basics.py
gonioanalysis/drosom/plotting/common.py
gonioanalysis/drosom/plotting/compare_opticflow.py
gonioanalysis/drosom/plotting/illustrate_experiments.py
gonioanalysis/drosom/plotting/start_position.py
gonioanalysis/drosom/reports/__init__.py
gonioanalysis/drosom/reports/displacement.py
gonioanalysis/drosom/reports/left_right.py
gonioanalysis/drosom/reports/pdf_summary.py
gonioanalysis/drosom/reports/stats.py
gonioanalysis/drosom/special/__init__.py
gonioanalysis/drosom/special/norpa_rescues.py
gonioanalysis/drosom/special/paired.py
gonioanalysis/drosox/analysing.py
gonioanalysis/drosox/loading.py
gonioanalysis/drosox/plotting.py
gonioanalysis/drosox/terminal.py
gonioanalysis/images/dpp.tif
gonioanalysis/images/droso_roll.png
gonioanalysis/images/from_mikko.png
gonioanalysis/images/from_mikko_annotated.png
gonioanalysis/images/mikkos_alternative_fly.png
gonioanalysis/images/rotation_roll.png
gonio_analysis-0.8.10.dist-info/METADATA
gonio_analysis-0.8.10.dist-info/WHEEL
gonio_analysis-0.8.10.dist-info/top_level.txt
gonio_analysis-0.8.10.dist-info/RECORD
