Metadata-Version: 2.4
Name: gonio-analysis
Version: 0.8.10
Summary: Spatial motion analysis program
Home-page: https://github.com/musaprog/gonio-analysis
Author: Joni Kemppainen
Author-email: joni.kemppainen@windowslive.com
Classifier: Programming Language :: Python :: 3
Classifier: License :: OSI Approved :: GNU General Public License v3 (GPLv3)
Classifier: Operating System :: OS Independent
Requires-Python: >=3.6
License-File: LICENSE
Requires-Dist: numpy
Requires-Dist: scipy
Requires-Dist: tifffile
Requires-Dist: matplotlib
Requires-Dist: tk-steroids>=0.8.1
Requires-Dist: roimarker>=0.2.1
Requires-Dist: movemeter>=0.7.2
Requires-Dist: python-biosystfiles
Requires-Dist: devjoni-hosguibase>=0.0.7
Requires-Dist: Panda3D>=1.10.0
Dynamic: author
Dynamic: author-email
Dynamic: classifier
Dynamic: description
Dynamic: description-content-type
Dynamic: home-page
Dynamic: license-file
Dynamic: requires-dist
Dynamic: requires-python
Dynamic: summary
